{
  "firstLayout": "",
  "gdVersion": {
    "build": 99,
    "major": 4,
    "minor": 0,
    "revision": 0
  },
  "properties": {
    "adaptGameResolutionAtRuntime": true,
    "antialiasingMode": "MSAA",
    "antialisingEnabledOnMobile": false,
    "folderProject": false,
    "orientation": "default",
    "packageName": "com.example.gamename",
    "pixelsRounding": true,
    "projectUuid": "74b1450a-86e6-4e78-8db8-2cdc0f53fcb6",
    "scaleMode": "nearest",
    "sizeOnStartupMode": "adaptWidth",
    "templateSlug": "",
    "useExternalSourceFiles": false,
    "version": "1.0.0",
    "name": "PrisonEscape",
    "description": "",
    "author": "",
    "windowWidth": 800,
    "windowHeight": 640,
    "latestCompilationDirectory": "",
    "maxFPS": 60,
    "minFPS": 20,
    "verticalSync": false,
    "platformSpecificAssets": {},
    "loadingScreen": {
      "backgroundColor": 0,
      "backgroundFadeInDuration": 0.2,
      "backgroundImageResourceName": "",
      "gdevelopLogoStyle": "light",
      "logoAndProgressFadeInDuration": 0.2,
      "logoAndProgressLogoFadeInDelay": 0,
      "minDuration": 1.5,
      "progressBarColor": 16777215,
      "progressBarHeight": 20,
      "progressBarMaxWidth": 200,
      "progressBarMinWidth": 40,
      "progressBarWidthPercent": 30,
      "showGDevelopSplash": true,
      "showProgressBar": true
    },
    "watermark": {
      "placement": "bottom-left",
      "showWatermark": true
    },
    "authorIds": [],
    "authorUsernames": [],
    "categories": [],
    "playableDevices": [],
    "extensionProperties": [],
    "platforms": [
      {
        "name": "GDevelop JS platform"
      }
    ],
    "currentPlatform": "GDevelop JS platform"
  },
  "resources": {
    "resources": [
      {
        "alwaysLoaded": false,
        "file": "assets/ground_part.png",
        "kind": "image",
        "metadata": "",
        "name": "assets\\ground_part.png",
        "smoothed": false,
        "userAdded": false
      },
      {
        "alwaysLoaded": false,
        "file": "assets/black.png",
        "kind": "image",
        "metadata": "",
        "name": "assets\\black.png",
        "smoothed": false,
        "userAdded": true
      },
      {
        "alwaysLoaded": false,
        "file": "assets/platform.png",
        "kind": "image",
        "metadata": "",
        "name": "assets\\platform.png",
        "smoothed": false,
        "userAdded": false
      },
      {
        "alwaysLoaded": false,
        "file": "assets/player.png",
        "kind": "image",
        "metadata": "",
        "name": "assets\\player.png",
        "smoothed": false,
        "userAdded": false
      },
      {
        "alwaysLoaded": false,
        "file": "assets/ground_part_2.png",
        "kind": "image",
        "metadata": "",
        "name": "assets\\ground_part_2.png",
        "smoothed": false,
        "userAdded": false
      },
      {
        "alwaysLoaded": false,
        "file": "assets/guard.png",
        "kind": "image",
        "metadata": "",
        "name": "assets\\guard.png",
        "smoothed": false,
        "userAdded": true
      }
    ],
    "resourceFolders": []
  },
  "objects": [],
  "objectsFolderStructure": {
    "folderName": "__ROOT"
  },
  "objectsGroups": [],
  "variables": [
    {
      "folded": true,
      "name": "BaseSpeed",
      "type": "string",
      "value": "60"
    }
  ],
  "layouts": [
    {
      "b": 209,
      "disableInputWhenNotFocused": true,
      "mangledName": "Level",
      "name": "Level",
      "r": 209,
      "standardSortMethod": true,
      "stopSoundsOnStartup": true,
      "title": "",
      "v": 209,
      "uiSettings": {
        "grid": true,
        "gridType": "rectangular",
        "gridWidth": 32,
        "gridHeight": 32,
        "gridOffsetX": 0,
        "gridOffsetY": 0,
        "gridColor": 10401023,
        "gridAlpha": 0.8,
        "snap": true,
        "zoomFactor": 0.9991260522560024,
        "windowMask": false
      },
      "objectsGroups": [],
      "variables": [
        {
          "folded": true,
          "name": "CooldownTime",
          "type": "number",
          "value": 0
        },
        {
          "folded": true,
          "name": "CooldownTimeMinimum",
          "type": "number",
          "value": 1
        },
        {
          "folded": true,
          "name": "CooldownTimeMaximum",
          "type": "number",
          "value": 4
        },
        {
          "folded": true,
          "name": "LevelNumber",
          "type": "number",
          "value": 0
        },
        {
          "folded": true,
          "name": "Side",
          "type": "number",
          "value": 0
        },
        {
          "folded": true,
          "name": "Paused",
          "type": "boolean",
          "value": false
        },
        {
          "folded": true,
          "name": "Lives",
          "type": "number",
          "value": 4
        }
      ],
      "instances": [
        {
          "angle": 0,
          "customSize": true,
          "depth": 0,
          "height": 32,
          "layer": "",
          "name": "Ground",
          "persistentUuid": "1cb3132f-a18b-4a69-a12e-09c940f9ddaa",
          "width": 800,
          "x": 0,
          "y": 288,
          "zOrder": 1,
          "numberProperties": [
            {
              "name": "animation",
              "value": 0
            }
          ],
          "stringProperties": [],
          "initialVariables": []
        },
        {
          "angle": 0,
          "customSize": true,
          "depth": 0,
          "height": 256,
          "layer": "",
          "name": "Black",
          "persistentUuid": "3a3450e5-66f8-4b1b-9185-7a34a79aa7e1",
          "width": 800,
          "x": 0,
          "y": 320,
          "zOrder": 2,
          "numberProperties": [],
          "stringProperties": [],
          "initialVariables": []
        },
        {
          "angle": 0,
          "customSize": true,
          "depth": 0,
          "height": 256,
          "layer": "",
          "name": "Black",
          "persistentUuid": "dc10fd1b-da60-45f0-8e89-321d29189d28",
          "width": 800,
          "x": 0,
          "y": 32,
          "zOrder": 2,
          "numberProperties": [],
          "stringProperties": [],
          "initialVariables": []
        },
        {
          "angle": 0,
          "customSize": true,
          "depth": 1,
          "height": 32,
          "layer": "",
          "name": "Platform",
          "persistentUuid": "f0a972ce-27bd-45b2-a2ae-cd72598d493b",
          "width": 64,
          "x": 348,
          "y": 510,
          "zOrder": 3,
          "numberProperties": [],
          "stringProperties": [],
          "initialVariables": [
            {
              "folded": true,
              "name": "SpeedFactor",
              "type": "number",
              "value": 1
            }
          ]
        },
        {
          "angle": 0,
          "customSize": false,
          "height": 0,
          "layer": "Entities",
          "name": "Player",
          "persistentUuid": "af1f6f66-2c9b-44cf-b539-ee766495f738",
          "width": 0,
          "x": 384,
          "y": 592,
          "zOrder": 5,
          "numberProperties": [],
          "stringProperties": [],
          "initialVariables": []
        },
        {
          "angle": 0,
          "customSize": true,
          "depth": 1,
          "height": 64,
          "layer": "",
          "name": "GroundPart2",
          "persistentUuid": "91eec23a-9679-482a-ad3b-07776b00c69c",
          "width": 800,
          "x": 0,
          "y": 576,
          "zOrder": 6,
          "numberProperties": [],
          "stringProperties": [],
          "initialVariables": []
        },
        {
          "angle": 0,
          "customSize": false,
          "height": 0,
          "layer": "Entities",
          "name": "Guard",
          "persistentUuid": "fbf6111a-93c1-438e-bbab-6dbb1b6c537c",
          "width": 0,
          "x": 0,
          "y": 416,
          "zOrder": 7,
          "numberProperties": [],
          "stringProperties": [],
          "initialVariables": []
        },
        {
          "angle": 0,
          "customSize": true,
          "depth": 1,
          "height": 32,
          "layer": "Entities",
          "name": "LevelEnd",
          "persistentUuid": "9735624f-e1a5-4cb4-8463-59ea213dac1e",
          "width": 800,
          "x": 0,
          "y": 0,
          "zOrder": 8,
          "numberProperties": [],
          "stringProperties": [],
          "initialVariables": []
        }
      ],
      "objects": [
        {
          "adaptCollisionMaskAutomatically": true,
          "assetStoreId": "",
          "name": "Ground",
          "type": "Sprite",
          "updateIfNotVisible": false,
          "variables": [],
          "effects": [],
          "behaviors": [],
          "animations": [
            {
              "name": "",
              "useMultipleDirections": false,
              "directions": [
                {
                  "looping": false,
                  "timeBetweenFrames": 0.08,
                  "sprites": [
                    {
                      "hasCustomCollisionMask": true,
                      "image": "assets\\ground_part.png",
                      "points": [],
                      "originPoint": {
                        "name": "origine",
                        "x": 0,
                        "y": 0
                      },
                      "centerPoint": {
                        "automatic": true,
                        "name": "centre",
                        "x": 0,
                        "y": 0
                      },
                      "customCollisionMask": [
                        [
                          {
                            "x": 0,
                            "y": 0
                          },
                          {
                            "x": 16,
                            "y": 0
                          },
                          {
                            "x": 16,
                            "y": 8
                          },
                          {
                            "x": 0,
                            "y": 8
                          }
                        ]
                      ]
                    }
                  ]
                }
              ]
            }
          ]
        },
        {
          "assetStoreId": "",
          "height": 32,
          "name": "Black",
          "texture": "assets\\black.png",
          "type": "TiledSpriteObject::TiledSprite",
          "width": 32,
          "variables": [],
          "effects": [],
          "behaviors": []
        },
        {
          "adaptCollisionMaskAutomatically": true,
          "assetStoreId": "",
          "name": "Player",
          "type": "Sprite",
          "updateIfNotVisible": false,
          "variables": [
            {
              "folded": true,
              "name": "Speed",
              "type": "number",
              "value": 40
            }
          ],
          "effects": [],
          "behaviors": [],
          "animations": [
            {
              "name": "",
              "useMultipleDirections": false,
              "directions": [
                {
                  "looping": false,
                  "timeBetweenFrames": 0.08,
                  "sprites": [
                    {
                      "hasCustomCollisionMask": true,
                      "image": "assets\\player.png",
                      "points": [],
                      "originPoint": {
                        "name": "origine",
                        "x": 0,
                        "y": 0
                      },
                      "centerPoint": {
                        "automatic": true,
                        "name": "centre",
                        "x": 0,
                        "y": 0
                      },
                      "customCollisionMask": [
                        [
                          {
                            "x": 3,
                            "y": 6
                          },
                          {
                            "x": 29,
                            "y": 6
                          },
                          {
                            "x": 29,
                            "y": 32
                          },
                          {
                            "x": 3,
                            "y": 32
                          }
                        ]
                      ]
                    }
                  ]
                }
              ]
            }
          ]
        },
        {
          "adaptCollisionMaskAutomatically": true,
          "assetStoreId": "",
          "name": "GroundPart2",
          "type": "Sprite",
          "updateIfNotVisible": false,
          "variables": [],
          "effects": [],
          "behaviors": [],
          "animations": [
            {
              "name": "",
              "useMultipleDirections": false,
              "directions": [
                {
                  "looping": false,
                  "timeBetweenFrames": 0.08,
                  "sprites": [
                    {
                      "hasCustomCollisionMask": true,
                      "image": "assets\\ground_part_2.png",
                      "points": [],
                      "originPoint": {
                        "name": "origine",
                        "x": 0,
                        "y": 0
                      },
                      "centerPoint": {
                        "automatic": true,
                        "name": "centre",
                        "x": 0,
                        "y": 0
                      },
                      "customCollisionMask": [
                        [
                          {
                            "x": 0,
                            "y": 0
                          },
                          {
                            "x": 16,
                            "y": 0
                          },
                          {
                            "x": 16,
                            "y": 16
                          },
                          {
                            "x": 0,
                            "y": 16
                          }
                        ]
                      ]
                    }
                  ]
                }
              ]
            }
          ]
        },
        {
          "adaptCollisionMaskAutomatically": true,
          "assetStoreId": "",
          "name": "Guard",
          "type": "Sprite",
          "updateIfNotVisible": false,
          "variables": [
            {
              "folded": true,
              "name": "Direction",
              "type": "number",
              "value": 1
            },
            {
              "folded": true,
              "name": "Speed",
              "type": "number",
              "value": 1
            }
          ],
          "effects": [],
          "behaviors": [],
          "animations": [
            {
              "name": "",
              "useMultipleDirections": false,
              "directions": [
                {
                  "looping": false,
                  "timeBetweenFrames": 0.08,
                  "sprites": [
                    {
                      "hasCustomCollisionMask": true,
                      "image": "assets\\guard.png",
                      "points": [],
                      "originPoint": {
                        "name": "origine",
                        "x": 0,
                        "y": 0
                      },
                      "centerPoint": {
                        "automatic": true,
                        "name": "centre",
                        "x": 0,
                        "y": 0
                      },
                      "customCollisionMask": [
                        [
                          {
                            "x": 3,
                            "y": 6
                          },
                          {
                            "x": 29,
                            "y": 6
                          },
                          {
                            "x": 29,
                            "y": 32
                          },
                          {
                            "x": 3,
                            "y": 32
                          }
                        ]
                      ]
                    }
                  ]
                }
              ]
            }
          ]
        },
        {
          "adaptCollisionMaskAutomatically": true,
          "assetStoreId": "",
          "name": "LevelEnd",
          "type": "Sprite",
          "updateIfNotVisible": false,
          "variables": [],
          "effects": [],
          "behaviors": [],
          "animations": [
            {
              "name": "",
              "useMultipleDirections": false,
              "directions": [
                {
                  "looping": false,
                  "timeBetweenFrames": 0.08,
                  "sprites": [
                    {
                      "hasCustomCollisionMask": true,
                      "image": "assets\\ground_part.png",
                      "points": [],
                      "originPoint": {
                        "name": "origine",
                        "x": 0,
                        "y": 0
                      },
                      "centerPoint": {
                        "automatic": true,
                        "name": "centre",
                        "x": 0,
                        "y": 0
                      },
                      "customCollisionMask": [
                        [
                          {
                            "x": 0,
                            "y": 0
                          },
                          {
                            "x": 16,
                            "y": 0
                          },
                          {
                            "x": 16,
                            "y": 8
                          },
                          {
                            "x": 0,
                            "y": 8
                          }
                        ]
                      ]
                    }
                  ]
                }
              ]
            }
          ]
        }
      ],
      "objectsFolderStructure": {
        "folderName": "__ROOT",
        "children": [
          {
            "objectName": "Ground"
          },
          {
            "objectName": "LevelEnd"
          },
          {
            "objectName": "Black"
          },
          {
            "objectName": "Player"
          },
          {
            "objectName": "GroundPart2"
          },
          {
            "objectName": "Guard"
          }
        ]
      },
      "events": [
        {
          "type": "BuiltinCommonInstructions::Standard",
          "conditions": [],
          "actions": [
            {
              "type": {
                "value": "MettreX"
              },
              "parameters": [
                "Guard",
                "+",
                "Guard.Direction * Guard.Speed * GlobalVariable(BaseSpeed) * TimeDelta()"
              ]
            }
          ]
        },
        {
          "type": "BuiltinCommonInstructions::Standard",
          "conditions": [
            {
              "type": {
                "value": "DepartScene"
              },
              "parameters": [
                ""
              ]
            }
          ],
          "actions": [
            {
              "type": {
                "value": "ResetTimer"
              },
              "parameters": [
                "",
                "\"PauseTime\""
              ]
            },
            {
              "type": {
                "value": "SetSceneVariableAsBoolean"
              },
              "parameters": [
                "Paused",
                "True"
              ]
            }
          ]
        },
        {
          "type": "BuiltinCommonInstructions::Standard",
          "conditions": [
            {
              "type": {
                "value": "CompareTimer"
              },
              "parameters": [
                "",
                "\"PauseTime\"",
                ">=",
                "5"
              ]
            }
          ],
          "actions": [
            {
              "type": {
                "value": "ResetTimer"
              },
              "parameters": [
                "",
                "\"SpawnTimer\""
              ]
            },
            {
              "type": {
                "value": "ModVarScene"
              },
              "parameters": [
                "Side",
                "=",
                "RandomInRange(0, 1)"
              ]
            },
            {
              "type": {
                "value": "ModVarScene"
              },
              "parameters": [
                "CooldownTime",
                "=",
                "RandomFloatInRange(Variable(CooldownTimeMinimum), Variable(CooldownTimeMaximum))"
              ]
            }
          ]
        },
        {
          "type": "BuiltinCommonInstructions::Standard",
          "conditions": [
            {
              "type": {
                "value": "BuiltinCommonInstructions::CompareNumbers"
              },
              "parameters": [
                "TimerElapsedTime(\"SpawnTimer\")",
                ">",
                "Variable(CooldownTime)"
              ]
            }
          ],
          "actions": [
            {
              "type": {
                "value": "ResetTimer"
              },
              "parameters": [
                "",
                "\"SpawnTimer\""
              ]
            },
            {
              "type": {
                "value": "ModVarScene"
              },
              "parameters": [
                "CooldownTime",
                "=",
                "RandomFloatInRange(Variable(CooldownTimeMinimum), Variable(CooldownTimeMaximum))"
              ]
            }
          ],
          "events": [
            {
              "type": "BuiltinCommonInstructions::Standard",
              "conditions": [
                {
                  "type": {
                    "value": "VarScene"
                  },
                  "parameters": [
                    "Side",
                    "=",
                    "0"
                  ]
                }
              ],
              "actions": [
                {
                  "type": {
                    "value": "Create"
                  },
                  "parameters": [
                    "",
                    "Guard",
                    "0",
                    "32*RandomInRange(1, 8)+RandomInRange(0, 1)*288",
                    "\"Entities\""
                  ]
                },
                {
                  "type": {
                    "value": "ModVarScene"
                  },
                  "parameters": [
                    "Side",
                    "=",
                    "RandomInRange(0, 1)"
                  ]
                },
                {
                  "type": {
                    "value": "ModVarObjet"
                  },
                  "parameters": [
                    "Guard",
                    "Direction",
                    "=",
                    "1"
                  ]
                }
              ]
            },
            {
              "type": "BuiltinCommonInstructions::Standard",
              "conditions": [
                {
                  "type": {
                    "value": "VarScene"
                  },
                  "parameters": [
                    "Side",
                    "=",
                    "1"
                  ]
                }
              ],
              "actions": [
                {
                  "type": {
                    "value": "Create"
                  },
                  "parameters": [
                    "",
                    "Guard",
                    "768",
                    "32*RandomInRange(1, 8)+RandomInRange(0, 1)*288",
                    "\"Entities\""
                  ]
                },
                {
                  "type": {
                    "value": "ModVarScene"
                  },
                  "parameters": [
                    "Side",
                    "=",
                    "RandomInRange(0, 1)"
                  ]
                },
                {
                  "type": {
                    "value": "ModVarObjet"
                  },
                  "parameters": [
                    "Guard",
                    "Direction",
                    "=",
                    "-1"
                  ]
                }
              ]
            }
          ]
        },
        {
          "colorB": 228,
          "colorG": 176,
          "colorR": 74,
          "creationTime": 0,
          "name": "movement",
          "source": "",
          "type": "BuiltinCommonInstructions::Group",
          "events": [
            {
              "type": "BuiltinCommonInstructions::Standard",
              "conditions": [
                {
                  "type": {
                    "value": "KeyPressed"
                  },
                  "parameters": [
                    "",
                    "Left"
                  ]
                }
              ],
              "actions": [
                {
                  "type": {
                    "value": "MettreX"
                  },
                  "parameters": [
                    "Player",
                    "=",
                    "max(0, Player.X() - TimeDelta() * Player.Speed)"
                  ]
                }
              ]
            },
            {
              "type": "BuiltinCommonInstructions::Standard",
              "conditions": [
                {
                  "type": {
                    "value": "KeyPressed"
                  },
                  "parameters": [
                    "",
                    "Right"
                  ]
                }
              ],
              "actions": [
                {
                  "type": {
                    "value": "MettreX"
                  },
                  "parameters": [
                    "Player",
                    "=",
                    "min(768, Player.X() + TimeDelta() * Player.Speed)"
                  ]
                }
              ]
            },
            {
              "type": "BuiltinCommonInstructions::Standard",
              "conditions": [
                {
                  "type": {
                    "value": "KeyPressed"
                  },
                  "parameters": [
                    "",
                    "Up"
                  ]
                }
              ],
              "actions": [
                {
                  "type": {
                    "value": "MettreY"
                  },
                  "parameters": [
                    "Player",
                    "=",
                    "max(0, Player.Y() - TimeDelta() * Player.Speed)"
                  ]
                }
              ]
            },
            {
              "type": "BuiltinCommonInstructions::Standard",
              "conditions": [
                {
                  "type": {
                    "value": "KeyPressed"
                  },
                  "parameters": [
                    "",
                    "Down"
                  ]
                }
              ],
              "actions": [
                {
                  "type": {
                    "value": "MettreY"
                  },
                  "parameters": [
                    "Player",
                    "=",
                    "min(608, Player.Y() + TimeDelta() * Player.Speed)"
                  ]
                }
              ]
            }
          ],
          "parameters": []
        },
        {
          "type": "BuiltinCommonInstructions::Standard",
          "conditions": [
            {
              "type": {
                "value": "PosY"
              },
              "parameters": [
                "Player",
                "<=",
                "8"
              ]
            }
          ],
          "actions": [
            {
              "type": {
                "value": "ModVarScene"
              },
              "parameters": [
                "LevelNumber",
                "+",
                "1"
              ]
            }
          ],
          "events": [
            {
              "type": "BuiltinCommonInstructions::Comment",
              "color": {
                "b": 109,
                "g": 230,
                "r": 255,
                "textB": 0,
                "textG": 0,
                "textR": 0
              },
              "comment": "screen win"
            }
          ]
        },
        {
          "type": "BuiltinCommonInstructions::Standard",
          "conditions": [
            {
              "type": {
                "value": "CollisionNP"
              },
              "parameters": [
                "Player",
                "Guard",
                "",
                "",
                ""
              ]
            }
          ],
          "actions": [
            {
              "type": {
                "value": "ResetTimer"
              },
              "parameters": [
                "",
                "\"PauseTime\""
              ]
            },
            {
              "type": {
                "value": "SetSceneVariableAsBoolean"
              },
              "parameters": [
                "Paused",
                "True"
              ]
            },
            {
              "type": {
                "value": "MettreXY"
              },
              "parameters": [
                "Player",
                "=",
                "384",
                "=",
                "592"
              ]
            },
            {
              "type": {
                "value": "ModVarScene"
              },
              "parameters": [
                "Lives",
                "-",
                "1"
              ]
            }
          ],
          "events": [
            {
              "type": "BuiltinCommonInstructions::Comment",
              "color": {
                "b": 109,
                "g": 230,
                "r": 255,
                "textB": 0,
                "textG": 0,
                "textR": 0
              },
              "comment": "death"
            }
          ]
        },
        {
          "type": "BuiltinCommonInstructions::Standard",
          "conditions": [
            {
              "type": {
                "value": "VarScene"
              },
              "parameters": [
                "Lives",
                "<=",
                "0"
              ]
            },
            {
              "type": {
                "value": "BuiltinCommonInstructions::Once"
              },
              "parameters": []
            }
          ],
          "actions": [],
          "events": [
            {
              "type": "BuiltinCommonInstructions::Comment",
              "color": {
                "b": 109,
                "g": 230,
                "r": 255,
                "textB": 0,
                "textG": 0,
                "textR": 0
              },
              "comment": "game over"
            }
          ]
        }
      ],
      "layers": [
        {
          "ambientLightColorB": 200,
          "ambientLightColorG": 200,
          "ambientLightColorR": 200,
          "camera3DFarPlaneDistance": 10000,
          "camera3DFieldOfView": 45,
          "camera3DNearPlaneDistance": 3,
          "cameraType": "",
          "followBaseLayerCamera": false,
          "isLightingLayer": false,
          "isLocked": false,
          "name": "",
          "renderingType": "",
          "visibility": true,
          "cameras": [
            {
              "defaultSize": true,
              "defaultViewport": true,
              "height": 0,
              "viewportBottom": 1,
              "viewportLeft": 0,
              "viewportRight": 1,
              "viewportTop": 0,
              "width": 0
            }
          ],
          "effects": [
            {
              "effectType": "Scene3D::HemisphereLight",
              "name": "3D Light",
              "doubleParameters": {
                "elevation": 45,
                "intensity": 1,
                "rotation": 0
              },
              "stringParameters": {
                "groundColor": "64;64;64",
                "skyColor": "255;255;255",
                "top": "Y-"
              },
              "booleanParameters": {}
            }
          ]
        },
        {
          "ambientLightColorB": 200,
          "ambientLightColorG": 200,
          "ambientLightColorR": 200,
          "camera3DFarPlaneDistance": 10000,
          "camera3DFieldOfView": 45,
          "camera3DNearPlaneDistance": 3,
          "cameraType": "",
          "followBaseLayerCamera": false,
          "isLightingLayer": false,
          "isLocked": false,
          "name": "Entities",
          "renderingType": "",
          "visibility": true,
          "cameras": [],
          "effects": [
            {
              "effectType": "Scene3D::HemisphereLight",
              "name": "3D Light",
              "doubleParameters": {
                "elevation": 45,
                "intensity": 1,
                "rotation": 0
              },
              "stringParameters": {
                "groundColor": "64;64;64",
                "skyColor": "255;255;255",
                "top": "Y-"
              },
              "booleanParameters": {}
            }
          ]
        }
      ],
      "behaviorsSharedData": [
        {
          "name": "Animation",
          "type": "AnimatableCapability::AnimatableBehavior"
        },
        {
          "name": "Effect",
          "type": "EffectCapability::EffectBehavior"
        },
        {
          "name": "Flippable",
          "type": "FlippableCapability::FlippableBehavior"
        },
        {
          "name": "Opacity",
          "type": "OpacityCapability::OpacityBehavior"
        },
        {
          "name": "Resizable",
          "type": "ResizableCapability::ResizableBehavior"
        },
        {
          "name": "Scale",
          "type": "ScalableCapability::ScalableBehavior"
        }
      ]
    }
  ],
  "externalEvents": [],
  "eventsFunctionsExtensions": [],
  "externalLayouts": [],
  "externalSourceFiles": []
}